saslibpy/__init__.py
saslibpy/_version.py
saslibpy/attestation.py
saslibpy/credential.py
saslibpy/requirements.txt
saslibpy/sas.py
saslibpy/schema.py
saslibpy-0.2.3.dist-info/METADATA
saslibpy-0.2.3.dist-info/WHEEL
saslibpy-0.2.3.dist-info/licenses/LICENSE
saslibpy-0.2.3.dist-info/RECORD
