Metadata-Version: 2.4
Name: saslibpy
Version: 0.2.3
Summary: python SDK for solana attestation service
Project-URL: Homepage, https://github.com/TrustaLabs/sas_python_lib
Author-email: Todd Li <liheact@gmail.com>
License-Expression: MIT
License-File: LICENSE
Classifier: Operating System :: OS Independent
Classifier: Programming Language :: Python :: 3
Requires-Python: >=3.10
Requires-Dist: borsh-construct>=0.1.0
Requires-Dist: solana>=0.36.6
Requires-Dist: solders>=0.26.0
